gcloudy/BigQuery.py
gcloudy/CloudFunctions.py
gcloudy/Extras.py
gcloudy/GoogleCloud.py
gcloudy/__init__.py
gcloudy-3.0.1.dist-info/licenses/LICENSE.md
gcloudy-3.0.1.dist-info/METADATA
gcloudy-3.0.1.dist-info/WHEEL
gcloudy-3.0.1.dist-info/top_level.txt
gcloudy-3.0.1.dist-info/RECORD
