Metadata-Version: 2.4
Name: gcloudy
Version: 3.0.1
Summary: A more intuitive approach to using Google's existing Google Cloud Platform (GCP) framework of cloud services in Python
Home-page: https://tomathon.dev/articles/gcloudy
Author: tomathon
Author-email: tomathon.dev@pm.me
License: GPL-3
Project-URL: Bug Tracker, https://codeberg.org/tomathon/gcloudy/issues
Classifier: Programming Language :: Python :: 3
Classifier: License :: OSI Approved :: MIT License
Classifier: Operating System :: OS Independent
Requires-Python: >=3.6
License-File: LICENSE.md
Dynamic: license-file
